judge/__init__.py
judge/ab_tests.py
judge/datamart_models.py
judge/unit_tests.py
minos_judge-0.1.1.dist-info/METADATA
minos_judge-0.1.1.dist-info/WHEEL
minos_judge-0.1.1.dist-info/top_level.txt
minos_judge-0.1.1.dist-info/RECORD
